cogsgpt/__init__.py
cogsgpt/awesome_chat.py
cogsgpt/llm.py
cogsgpt/logger.py
cogsgpt/schema.py
cogsgpt/utils.py
cogsgpt/cogsmodel/__init__.py
cogsgpt/cogsmodel/base_model.py
cogsgpt/cogsmodel/cv/__init__.py
cogsgpt/cogsmodel/cv/background_remover.py
cogsgpt/cogsmodel/cv/form_recognizer.py
cogsgpt/cogsmodel/cv/image_analysis_v3.py
cogsgpt/cogsmodel/cv/image_analysis_v4.py
cogsgpt/cogsmodel/cv/utils.py
cogsgpt/cogsmodel/nlp/__init__.py
cogsgpt/cogsmodel/nlp/text_analysis.py
cogsgpt/cogsmodel/nlp/text_generation.py
cogsgpt/cogsmodel/nlp/text_summarize.py
cogsgpt/cogsmodel/nlp/text_translation.py
cogsgpt/cogsmodel/speech/__init__.py
cogsgpt/cogsmodel/speech/speech.py
cogsgpt/metas/generate_response_presteps.json
cogsgpt/metas/parse_task_presteps.json
cogsgpt/metas/prompts.yaml
cogsgpt/metas/task_metas.yaml
cogsgpt-1.0.2.dist-info/LICENSE
cogsgpt-1.0.2.dist-info/METADATA
cogsgpt-1.0.2.dist-info/WHEEL
cogsgpt-1.0.2.dist-info/top_level.txt
cogsgpt-1.0.2.dist-info/RECORD
