Metadata-Version: 2.1
Name: cogsgpt
Version: 1.0.2
Summary: A multi-modal LLM integrated ChatGPT with Azure Cognitive Service
Author-email: weitian <weitian.bnu@gmail.com>
License: MIT License
Project-URL: Homepage, https://github.com/whiskyboy/cogsgpt
Keywords: chatgpt,cognitive service,llm
Classifier: License :: OSI Approved :: MIT License
Classifier: Programming Language :: Python
Classifier: Programming Language :: Python :: 3
Requires-Python: >=3.8
License-File: LICENSE
Requires-Dist: azure-ai-vision
Requires-Dist: azure-cognitiveservices-vision-computervision
Requires-Dist: azure-ai-formrecognizer
Requires-Dist: azure-ai-textanalytics (==5.3.0b1)
Requires-Dist: azure-cognitiveservices-speech
Requires-Dist: colorlog
Requires-Dist: jinja2
Requires-Dist: langchain
Requires-Dist: openai
Requires-Dist: pillow
Requires-Dist: tiktoken
